{"id": "bibl__62654d5b-9579-4c97-a1a7-cdcf1b7c57ad", "browser_url": "https://www.freud-edition.net/werke/ueber-fecondite-von-emil-zola/druckversion", "url": "https://www.freud-edition.net/jsonapi/node/manifestation/62654d5b-9579-4c97-a1a7-cdcf1b7c57ad", "man_title": "Ueber \"Fecondit\u00e9\" von Emil Zola ", "signature": "1900-242/1932", "status": {"id": "0", "name": "proposed", "date": "2022-12-31"}, "man_doc_type": {"id": "5b8d9c77-99d0-4a80-92d8-4a9de06ac7ca", "type": "taxonomy_term--manifestation_art", "name": "Historische Ausgaben"}, "doc_component": {"id": "228361d0-4cda-4805-a2f8-a05ee58119b6", "type": "taxonomy_term--komponente", "name": "Vollst\u00e4ndige Manifestation"}, "note_i": null, "man_shorttitle": "Erw\u00e4hnung", "date": {"value": "1932-12-01", "end_value": "1932-12-01"}, "reihe": {"name": null, "number": null}, "page_num": {"start": "376"}, "man_type": "Druckversion", "man_font": [{"name": "Druckschrift"}], "man_format": "Buch", "man_mediatype": "Papier", "type": "Text in Periodikum", "man_lang": {}, "man_edition": null, "author": {"name": "Freud, Sigmund", "id": "p__80f26163-0581-4079-a0ce-4f2417f09b97", "tid": "111", "rev_id": "111", "url": "https://www.freud-edition.net/jsonapi/taxonomy_term/personen/80f26163-0581-4079-a0ce-4f2417f09b97", "browser_url": "https://www.freud-edition.net/taxonomy/term/111"}, "work": {"id": "bibl__145e341e-b96b-450f-b6c9-29283af531f6", "title": "Freud, Sigmund  (1900-242; 1900d): F\u00e9condit\u00e9 von \u00c9mile Zola [Erw\u00e4hnung]", "url": "https://www.freud-edition.net/jsonapi/node/werk/145e341e-b96b-450f-b6c9-29283af531f6", "browser_url": "https://www.freud-edition.net/fecondite-emile-zola"}, "publication": {"id": "bibl__d1dd6d37-53ef-43d9-b676-639100f159f9", "title": "B\u2019nai B\u2019rith Mitteilungen f\u00fcr \u00d6sterreich, 32, 1932,  10", "type": "Periodikum (Heft)", "reihe": {"name": null, "number": null}, "url": "https://www.freud-edition.net/jsonapi/node/bibliography/d1dd6d37-53ef-43d9-b676-639100f159f9", "title_main": "B\u2019nai B\u2019rith Mitteilungen f\u00fcr \u00d6sterreich", "jahrgang": "32", "original_publication_year": null, "places": [{"name": "Wien"}], "date": "1932-12-01", "band": {"name": "10", "number": 10}, "herausgeber": [{"id": "p__3fa8c116-147b-4088-b776-1907247ae5fe", "name": "Ascher, Arnold", "url": "https://www.freud-edition.net/jsonapi/taxonomy_term/personen/3fa8c116-147b-4088-b776-1907247ae5fe", "tid": 4039, "rev_id": 4039, "browser_url": "https://www.freud-edition.net/taxonomy/term/4039"}], "publication": {"id": "bibl__58263c50-c7a6-430f-aa36-e86e85dd8f88", "title": "B\u2019nai B\u2019rith Mitteilungen f\u00fcr \u00d6sterreich, 32, 1932", "type": "Periodikum (Jahrgang)", "reihe": {"name": null, "number": null}, "url": "https://www.freud-edition.net/jsonapi/node/bibliography/58263c50-c7a6-430f-aa36-e86e85dd8f88", "title_main": "B\u2019nai B\u2019rith Mitteilungen f\u00fcr \u00d6sterreich", "jahrgang": "32", "original_publication_year": null, "places": [{"name": "Wien"}], "date": "1932-01-01", "herausgeber": [{"id": "p__3fa8c116-147b-4088-b776-1907247ae5fe", "name": "Ascher, Arnold", "url": "https://www.freud-edition.net/jsonapi/taxonomy_term/personen/3fa8c116-147b-4088-b776-1907247ae5fe", "tid": 4039, "rev_id": 4039, "browser_url": "https://www.freud-edition.net/taxonomy/term/4039"}], "publication": {"id": "bibl__88591fbc-d26a-48ff-aa7b-5d609db19127", "title": "B\u2019nai B\u2019rith Mitteilungen f\u00fcr \u00d6sterreich", "type": "Periodikum", "reihe": {"name": null, "number": null}, "url": "https://www.freud-edition.net/jsonapi/node/bibliography/88591fbc-d26a-48ff-aa7b-5d609db19127", "title_main": "B\u2019nai B\u2019rith Mitteilungen f\u00fcr \u00d6sterreich", "original_publication_year": null, "date": null}}}, "repository": {"id": "rep__0fd1eab6-5292-468c-8d35-10d7345ea492", "name": "IPU", "url": "https://www.freud-edition.net/jsonapi/taxonomy_term/archive/0fd1eab6-5292-468c-8d35-10d7345ea492"}, "pages": [{"id": "beb4a23e-8e6f-4d11-841e-9463d1b10b0e", "title": "376", "page_nr": "376", "attr": {"drupal_internal__nid": 115965, "drupal_internal__vid": 156226, "langcode": "und", "revision_timestamp": 1643033942, "revision_log": null, "status": false, "title": "376", "created": 1643033942, "changed": 1643033942, "promote": false, "sticky": false, "default_langcode": true, "revision_translation_affected": true, "content_translation_source": "und", "content_translation_outdated": false, "metatag": null, "path": {"alias": null, "pid": null, "langcode": "und"}, "body": {"value": "<p>1. Am 23. J\u00e4nner 1900 von Br. Architekt Fleischer ,Uber<br />\r\nBruderschaftsbindnisse\".<br />\r\n2. Am 9. Februar 1900 von Br. Prof. Freud vor Damen<br />\r\n,\u00dcber das Seelenleben des Kindes\".<br />\r\n3. Am 27. Februar von Br. Bernhard Jerusalem ,Uber<br />\r\ndie landwirtschaftliche Aktion des zu gr\u00fcndenden Hilfs-<br />\r\nvereines f\u00fcr Galizien\".<br />\r\n4. Am 8. M\u00e4rz von Br. Architekten Fleischer vor Damen<br />\r\n, Aus meinen Erinnerungen an den Wiener Rathausbau\".<br />\r\n5. Am 27. M\u00e4rz von Prof. E hrmann \u00fcber ,J\u00fcdische Denker<br />\r\nzu Beginn unserer Zeitrechnung\".<br />\r\n6. Am 24. April von Br. Prof. Freud ,Uber Fecondit\u00e9 von<br />\r\nZola\".<br />\r\n7. Am 11. November von Br. Dr. Josef Jerusalem ,Uber<br />\r\nHaeckels Weltr\u00e4tsel\".</p>\r\n", "format": "filtered_html", "processed": "<p>1. Am 23. J\u00e4nner 1900 von Br. Architekt Fleischer ,Uber<br />\nBruderschaftsbindnisse\".<br />\n2. Am 9. Februar 1900 von Br. Prof. Freud vor Damen<br />\n,\u00dcber das Seelenleben des Kindes\".<br />\n3. Am 27. Februar von Br. Bernhard Jerusalem ,Uber<br />\ndie landwirtschaftliche Aktion des zu gr\u00fcndenden Hilfs-<br />\nvereines f\u00fcr Galizien\".<br />\n4. Am 8. M\u00e4rz von Br. Architekten Fleischer vor Damen<br />\n, Aus meinen Erinnerungen an den Wiener Rathausbau\".<br />\n5. Am 27. M\u00e4rz von Prof. E hrmann \u00fcber ,J\u00fcdische Denker<br />\nzu Beginn unserer Zeitrechnung\".<br />\n6. Am 24. April von Br. Prof. Freud ,Uber Fecondit\u00e9 von<br />\nZola\".<br />\n7. Am 11. November von Br. Dr. Josef Jerusalem ,Uber<br />\nHaeckels Weltr\u00e4tsel\".</p>", "summary": ""}}, "body": "<p>1. Am 23. J\u00e4nner 1900 von Br. Architekt Fleischer ,Uber<lb /> Bruderschaftsbindnisse\".<lb /> 2. Am 9. Februar 1900 von Br. Prof. Freud vor Damen<lb /> ,\u00dcber das Seelenleben des Kindes\".<lb /> 3. Am 27. Februar von Br. Bernhard Jerusalem ,Uber<lb /> die landwirtschaftliche Aktion des zu gr\u00fcndenden Hilfs<lb break=\"no\"/>vereines f\u00fcr Galizien\".<lb /> 4. Am 8. M\u00e4rz von Br. Architekten Fleischer vor Damen<lb /> , Aus meinen Erinnerungen an den Wiener Rathausbau\".<lb /> 5. Am 27. M\u00e4rz von Prof. E hrmann \u00fcber ,J\u00fcdische Denker<lb /> zu Beginn unserer Zeitrechnung\".<lb /> 6. Am 24. April von Br. Prof. Freud ,Uber Fecondit\u00e9 von<lb /> Zola\".<lb /> 7. Am 11. November von Br. Dr. Josef Jerusalem ,Uber<lb /> Haeckels Weltr\u00e4tsel\".<lb break=\"paragraph\"/></p>", "faks": {"type": "file--file", "id": "51dad604-2f34-44b1-b9a7-afef6df3f73f", "links": {"self": {"href": "http://www.freud-edition.net/jsonapi/file/file/51dad604-2f34-44b1-b9a7-afef6df3f73f"}}, "attributes": {"drupal_internal__fid": 83503, "langcode": "de", "filename": "bb_32_10_seelenleben_0_seite_1_0.jpg", "uri": {"value": "public://handschriften/bb_32_10_seelenleben_0_seite_1_0.jpg", "url": "/sites/default/files/handschriften/bb_32_10_seelenleben_0_seite_1_0.jpg"}, "filemime": "image/jpeg", "filesize": 1034674, "status": true, "created": 1643033819, "changed": 1643033945}, "relationships": {"uid": {"data": null, "links": {"self": {"href": "http://www.freud-edition.net/jsonapi/file/file/51dad604-2f34-44b1-b9a7-afef6df3f73f/relationships/uid"}}}}}, "faks__id": "51dad604-2f34-44b1-b9a7-afef6df3f73f", "faks__url": "http://www.freud-edition.net/jsonapi/file/file/51dad604-2f34-44b1-b9a7-afef6df3f73f", "faks__payload": "/sites/default/files/handschriften/bb_32_10_seelenleben_0_seite_1_0.jpg"}]}